mr_kot_fs_validators/__init__.py
mr_kot_fs_validators/validators.py
mr_kot_fs_validators-0.1.0.dist-info/METADATA
mr_kot_fs_validators-0.1.0.dist-info/WHEEL
mr_kot_fs_validators-0.1.0.dist-info/RECORD
