Metadata-Version: 2.3
Name: mr-kot-fs-validators
Version: 0.1.0
Summary: Reusable filesystem validators for Mr. Kot checks.
License: MIT
Author: Alexander Presniakov
Author-email: alexander.presniakov@mariadb.com
Requires-Python: >=3.9,<4.0
Classifier: Environment :: Console
Classifier: Intended Audience :: Developers
Classifier: License :: OSI Approved :: MIT License
Classifier: Operating System :: OS Independent
Classifier: Programming Language :: Python
Classifier: Programming Language :: Python :: 3
Classifier: Programming Language :: Python :: 3.9
Classifier: Programming Language :: Python :: 3.10
Classifier: Programming Language :: Python :: 3.11
Classifier: Programming Language :: Python :: 3.12
Classifier: Programming Language :: Python :: 3.13
Classifier: Programming Language :: Python :: Implementation :: CPython
Classifier: Topic :: Software Development :: Testing
Requires-Dist: mr-kot (>=0.8.1,<0.9.0)
